marm_mcp_server/__init__.py
marm_mcp_server/server.py
marm_mcp_server/config/__init__.py
marm_mcp_server/config/settings.py
marm_mcp_server/core/__init__.py
marm_mcp_server/core/events.py
marm_mcp_server/core/memory.py
marm_mcp_server/core/models.py
marm_mcp_server/core/rate_limiter.py
marm_mcp_server/core/response_limiter.py
marm_mcp_server/core/shutdown_manager.py
marm_mcp_server/core/websocket_manager.py
marm_mcp_server/endpoints/__init__.py
marm_mcp_server/endpoints/logging.py
marm_mcp_server/endpoints/memory.py
marm_mcp_server/endpoints/notebook.py
marm_mcp_server/endpoints/oauth.py
marm_mcp_server/endpoints/reasoning.py
marm_mcp_server/endpoints/session.py
marm_mcp_server/endpoints/system.py
marm_mcp_server/endpoints/websocket.py
marm_mcp_server/endpoints/websocket_handlers_complete.py
marm_mcp_server/middleware/__init__.py
marm_mcp_server/middleware/rate_limiting.py
marm_mcp_server/middleware/websocket_rate_limiting.py
marm_mcp_server/services/__init__.py
marm_mcp_server/services/automation.py
marm_mcp_server/services/documentation.py
marm_mcp_server/utils/__init__.py
marm_mcp_server/utils/helpers.py
marm_mcp_server-2.2.6.dist-info/METADATA
marm_mcp_server-2.2.6.dist-info/WHEEL
marm_mcp_server-2.2.6.dist-info/entry_points.txt
marm_mcp_server-2.2.6.dist-info/top_level.txt
marm_mcp_server-2.2.6.dist-info/RECORD
